Workbook

Sheet Dashboard
A1: JAYAKUMAR BEARINGS 112, Cotton Market, (Malayadipatti Street), Rajapalayam - 626117. Phone no.: 9942983003 Email: jkbearingrjpm@gmail.com GSTIN: 33ALEPP5843M2ZP, State: 33-Tamil Nadu
A2: ELGS 5.0 LOAN MANAGEMENT DASHBOARD
A5: LOAN PARAMETERS (INPUTS)
A6: Loan Amount (Principal) | B6: 199000
A7: Annual Interest Rate | B7: 0.0875
A8: Total Tenure (Months) | B8: 60
A9: Moratorium Period (Months) | B9: 12
A10: First Disbursal Date | B10: 46203
A11: Bank | B11: Canara Bank RJPM
A13: CALCULATED STRUCTURAL METRICS
A14: Year 1 Monthly Interest (Moratorium) | B14: =B6*(B7/12) -> 1451.0417
A15: Years 2-5 Monthly EMI | B15: =IFERROR(PMT(B7/12, B8-B9, -B6), 0) -> 4928.5342
A16: Total Interest Payable | B16: =SUM('Amortization Schedule'!F4:F63) -> 54982.12
A17: Total Capital Outlay | B17: =B6+B16 -> 253982.12

Sheet Amortization Schedule
A1: JAYAKUMAR BEARINGS 112, Cotton Market, (Malayadipatti Street), Rajapalayam - 626117. Phone no.: 9942983003 Email: jkbearingrjpm@gmail.com GSTIN: 33ALEPP5843M2ZP, State: 33-Tamil Nadu
A3: Month | B3: Payment Date | C3: Phase Indicator | D3: Beginning Balance | E3: Total Payment | F3: Interest Component | G3: Principal Component | H3: Ending Balance | I3: Cum. Interest | J3: Cum. Principal
A4: 1 | B4: =Dashboard!$B$10 -> 46203 | C4: =IF(A4<=Dashboard!$B$9, "Moratorium (Interest-Only)", "Repayment (EMI Phase)") -> Moratorium (Interest-Only) | D4: =Dashboard!$B$6 -> 199000 | E4: =IF(C4="Moratorium (Interest-Only)", Dashboard!$B$14, Dashboard!$B$15) -> 1451.0417 | F4: =ROUND(D4*(Dashboard!$B$7/12), 2) -> 1451.04 | G4: =ROUND(E4-F4, 2) -> 0 | H4: =D4-G4 -> 199000 | I4: =F4 -> 1451.04 | J4: =G4 -> 0
A5: 2 | B5: =EDATE(B4, 1) -> 46233 | C5: =IF(A5<=Dashboard!$B$9, "Moratorium (Interest-Only)", "Repayment (EMI Phase)") -> Moratorium (Interest-Only) | D5: =H4 -> 199000 | E5: =IF(C5="Moratorium (Interest-Only)", Dashboard!$B$14, Dashboard!$B$15) -> 1451.0417 | F5: =ROUND(D5*(Dashboard!$B$7/12), 2) -> 1451.04 | G5: =ROUND(E5-F5, 2) -> 0 | H5: =D5-G5 -> 199000 | I5: =I4+F5 -> 2902.08 | J5: =J4+G5 -> 0
A6: 3 | B6: =EDATE(B5, 1) -> 46264 | C6: =IF(A6<=Dashboard!$B$9, "Moratorium (Interest-Only)", "Repayment (EMI Phase)") -> Moratorium (Interest-Only) | D6: =H5 -> 199000 | E6: =IF(C6="Moratorium (Interest-Only)", Dashboard!$B$14, Dashboard!$B$15) -> 1451.0417 | F6: =ROUND(D6*(Dashboard!$B$7/12), 2) -> 1451.04 | G6: =ROUND(E6-F6, 2) -> 0 | H6: =D6-G6 -> 199000 | I6: =I5+F6 -> 4353.12 | J6: =J5+G6 -> 0
A7: 4 | B7: =EDATE(B6, 1) -> 46295 | C7: =IF(A7<=Dashboard!$B$9, "Moratorium (Interest-Only)", "Repayment (EMI Phase)") -> Moratorium (Interest-Only) | D7: =H6 -> 199000 | E7: =IF(C7="Moratorium (Interest-Only)", Dashboard!$B$14, Dashboard!$B$15) -> 1451.0417 | F7: =ROUND(D7*(Dashboard!$B$7/12), 2) -> 1451.04 | G7: =ROUND(E7-F7, 2) -> 0 | H7: =D7-G7 -> 199000 | I7: =I6+F7 -> 5804.16 | J7: =J6+G7 -> 0
A8: 5 | B8: =EDATE(B7, 1) -> 46325 | C8: =IF(A8<=Dashboard!$B$9, "Moratorium (Interest-Only)", "Repayment (EMI Phase)") -> Moratorium (Interest-Only) | D8: =H7 -> 199000 | E8: =IF(C8="Moratorium (Interest-Only)", Dashboard!$B$14, Dashboard!$B$15) -> 1451.0417 | F8: =ROUND(D8*(Dashboard!$B$7/12), 2) -> 1451.04 | G8: =ROUND(E8-F8, 2) -> 0 | H8: =D8-G8 -> 199000 | I8: =I7+F8 -> 7255.2 | J8: =J7+G8 -> 0
A9: 6 | B9: =EDATE(B8, 1) -> 46356 | C9: =IF(A9<=Dashboard!$B$9, "Moratorium (Interest-Only)", "Repayment (EMI Phase)") -> Moratorium (Interest-Only) | D9: =H8 -> 199000 | E9: =IF(C9="Moratorium (Interest-Only)", Dashboard!$B$14, Dashboard!$B$15) -> 1451.0417 | F9: =ROUND(D9*(Dashboard!$B$7/12), 2) -> 1451.04 | G9: =ROUND(E9-F9, 2) -> 0 | H9: =D9-G9 -> 199000 | I9: =I8+F9 -> 8706.24 | J9: =J8+G9 -> 0
A10: 7 | B10: =EDATE(B9, 1) -> 46386 | C10: =IF(A10<=Dashboard!$B$9, "Moratorium (Interest-Only)", "Repayment (EMI Phase)") -> Moratorium (Interest-Only) | D10: =H9 -> 199000 | E10: =IF(C10="Moratorium (Interest-Only)", Dashboard!$B$14, Dashboard!$B$15) -> 1451.0417 | F10: =ROUND(D10*(Dashboard!$B$7/12), 2) -> 1451.04 | G10: =ROUND(E10-F10, 2) -> 0 | H10: =D10-G10 -> 199000 | I10: =I9+F10 -> 10157.28 | J10: =J9+G10 -> 0
A11: 8 | B11: =EDATE(B10, 1) -> 46417 | C11: =IF(A11<=Dashboard!$B$9, "Moratorium (Interest-Only)", "Repayment (EMI Phase)") -> Moratorium (Interest-Only) | D11: =H10 -> 199000 | E11: =IF(C11="Moratorium (Interest-Only)", Dashboard!$B$14, Dashboard!$B$15) -> 1451.0417 | F11: =ROUND(D11*(Dashboard!$B$7/12), 2) -> 1451.04 | G11: =ROUND(E11-F11, 2) -> 0 | H11: =D11-G11 -> 199000 | I11: =I10+F11 -> 11608.32 | J11: =J10+G11 -> 0
A12: 9 | B12: =EDATE(B11, 1) -> 46446 | C12: =IF(A12<=Dashboard!$B$9, "Moratorium (Interest-Only)", "Repayment (EMI Phase)") -> Moratorium (Interest-Only) | D12: =H11 -> 199000 | E12: =IF(C12="Moratorium (Interest-Only)", Dashboard!$B$14, Dashboard!$B$15) -> 1451.0417 | F12: =ROUND(D12*(Dashboard!$B$7/12), 2) -> 1451.04 | G12: =ROUND(E12-F12, 2) -> 0 | H12: =D12-G12 -> 199000 | I12: =I11+F12 -> 13059.36 | J12: =J11+G12 -> 0
A13: 10 | B13: =EDATE(B12, 1) -> 46474 | C13: =IF(A13<=Dashboard!$B$9, "Moratorium (Interest-Only)", "Repayment (EMI Phase)") -> Moratorium (Interest-Only) | D13: =H12 -> 199000 | E13: =IF(C13="Moratorium (Interest-Only)", Dashboard!$B$14, Dashboard!$B$15) -> 1451.0417 | F13: =ROUND(D13*(Dashboard!$B$7/12), 2) -> 1451.04 | G13: =ROUND(E13-F13, 2) -> 0 | H13: =D13-G13 -> 199000 | I13: =I12+F13 -> 14510.4 | J13: =J12+G13 -> 0
A14: 11 | B14: =EDATE(B13, 1) -> 46505 | C14: =IF(A14<=Dashboard!$B$9, "Moratorium (Interest-Only)", "Repayment (EMI Phase)") -> Moratorium (Interest-Only) | D14: =H13 -> 199000 | E14: =IF(C14="Moratorium (Interest-Only)", Dashboard!$B$14, Dashboard!$B$15) -> 1451.0417 | F14: =ROUND(D14*(Dashboard!$B$7/12), 2) -> 1451.04 | G14: =ROUND(E14-F14, 2) -> 0 | H14: =D14-G14 -> 199000 | I14: =I13+F14 -> 15961.44 | J14: =J13+G14 -> 0
A15: 12 | B15: =EDATE(B14, 1) -> 46535 | C15: =IF(A15<=Dashboard!$B$9, "Moratorium (Interest-Only)", "Repayment (EMI Phase)") -> Moratorium (Interest-Only) | D15: =H14 -> 199000 | E15: =IF(C15="Moratorium (Interest-Only)", Dashboard!$B$14, Dashboard!$B$15) -> 1451.0417 | F15: =ROUND(D15*(Dashboard!$B$7/12), 2) -> 1451.04 | G15: =ROUND(E15-F15, 2) -> 0 | H15: =D15-G15 -> 199000 | I15: =I14+F15 -> 17412.48 | J15: =J14+G15 -> 0
A16: 13 | B16: =EDATE(B15, 1) -> 46566 | C16: =IF(A16<=Dashboard!$B$9, "Moratorium (Interest-Only)", "Repayment (EMI Phase)") -> Repayment (EMI Phase) | D16: =H15 -> 199000 | E16: =IF(C16="Moratorium (Interest-Only)", Dashboard!$B$14, Dashboard!$B$15) -> 4928.5342 | F16: =ROUND(D16*(Dashboard!$B$7/12), 2) -> 1451.04 | G16: =ROUND(E16-F16, 2) -> 3477.49 | H16: =D16-G16 -> 195522.51 | I16: =I15+F16 -> 18863.52 | J16: =J15+G16 -> 3477.49
... A62: 59 | B62: =EDATE(B61, 1) -> 47966 | C62: =IF(A62<=Dashboard!$B$9, "Moratorium (Interest-Only)", "Repayment (EMI Phase)") -> Repayment (EMI Phase) | D62: =H61 -> 9750.48 | E62: =IF(C62="Moratorium (Interest-Only)", Dashboard!$B$14, Dashboard!$B$15) -> 4928.5342 | F62: =ROUND(D62*(Dashboard!$B$7/12), 2) -> 71.1 | G62: =ROUND(E62-F62, 2) -> 4857.43 | H62: =D62-G62 -> 4893.05 | I62: =I61+F62 -> 54946.44 | J62: =J61+G62 -> 194106.95
A63: 60 | B63: =EDATE(B62, 1) -> 47996 | C63: =IF(A63<=Dashboard!$B$9, "Moratorium (Interest-Only)", "Repayment (EMI Phase)") -> Repayment (EMI Phase) | D63: =H62 -> 4893.05 | E63: =IF(C63="Moratorium (Interest-Only)", Dashboard!$B$14, Dashboard!$B$15) -> 4928.5342 | F63: =ROUND(D63*(Dashboard!$B$7/12), 2) -> 35.68 | G63: =D63 -> 4893.05 | H63: =D63-G63 -> 0 | I63: =I62+F63 -> 54982.12 | J63: =J62+G63 -> 199000

Sheet Yearly Summary
A1: JAYAKUMAR BEARINGS 112, Cotton Market, (Malayadipatti Street), Rajapalayam - 626117. Phone no.: 9942983003 Email: jkbearingrjpm@gmail.com GSTIN: 33ALEPP5843M2ZP, State: 33-Tamil Nadu
A4: Year | B4: Total Annual Payment | C4: Annual Principal Paid | D4: Annual Interest Paid | E4: Year-End Balance
A5: 1 | B5: =SUMIFS('Amortization Schedule'!E:E, 'Amortization Schedule'!A:A, ">="&((1-1)*12+1), 'Amortization Schedule'!A:A, "<="&(1*12)) -> 17412.5 | C5: =SUMIFS('Amortization Schedule'!G:G, 'Amortization Schedule'!A:A, ">="&((1-1)*12+1), 'Amortization Schedule'!A:A, "<="&(1*12)) -> 0 | D5: =SUMIFS('Amortization Schedule'!F:F, 'Amortization Schedule'!A:A, ">="&((1-1)*12+1), 'Amortization Schedule'!A:A, "<="&(1*12)) -> 17412.48 | E5: =IFERROR(INDEX('Amortization Schedule'!H:H, MATCH(1*12, 'Amortization Schedule'!A:A, 0)), 0) -> 199000
A6: 2 | B6: =SUMIFS('Amortization Schedule'!E:E, 'Amortization Schedule'!A:A, ">="&((2-1)*12+1), 'Amortization Schedule'!A:A, "<="&(2*12)) -> 59142.41 | C6: =SUMIFS('Amortization Schedule'!G:G, 'Amortization Schedule'!A:A, ">="&((2-1)*12+1), 'Amortization Schedule'!A:A, "<="&(2*12)) -> 43444.77 | D6: =SUMIFS('Amortization Schedule'!F:F, 'Amortization Schedule'!A:A, ">="&((2-1)*12+1), 'Amortization Schedule'!A:A, "<="&(2*12)) -> 15697.59 | E6: =IFERROR(INDEX('Amortization Schedule'!H:H, MATCH(2*12, 'Amortization Schedule'!A:A, 0)), 0) -> 155555.23
A7: 3 | B7: =SUMIFS('Amortization Schedule'!E:E, 'Amortization Schedule'!A:A, ">="&((3-1)*12+1), 'Amortization Schedule'!A:A, "<="&(3*12)) -> 59142.41 | C7: =SUMIFS('Amortization Schedule'!G:G, 'Amortization Schedule'!A:A, ">="&((3-1)*12+1), 'Amortization Schedule'!A:A, "<="&(3*12)) -> 47402.41 | D7: =SUMIFS('Amortization Schedule'!F:F, 'Amortization Schedule'!A:A, ">="&((3-1)*12+1), 'Amortization Schedule'!A:A, "<="&(3*12)) -> 11739.95 | E7: =IFERROR(INDEX('Amortization Schedule'!H:H, MATCH(3*12, 'Amortization Schedule'!A:A, 0)), 0) -> 108152.82
A8: 4 | B8: =SUMIFS('Amortization Schedule'!E:E, 'Amortization Schedule'!A:A, ">="&((4-1)*12+1), 'Amortization Schedule'!A:A, "<="&(4*12)) -> 59142.41 | C8: =SUMIFS('Amortization Schedule'!G:G, 'Amortization Schedule'!A:A, ">="&((4-1)*12+1), 'Amortization Schedule'!A:A, "<="&(4*12)) -> 51720.55 | D8: =SUMIFS('Amortization Schedule'!F:F, 'Amortization Schedule'!A:A, ">="&((4-1)*12+1), 'Amortization Schedule'!A:A, "<="&(4*12)) -> 7421.81 | E8: =IFERROR(INDEX('Amortization Schedule'!H:H, MATCH(4*12, 'Amortization Schedule'!A:A, 0)), 0) -> 56432.27
A9: 5 | B9: =SUMIFS('Amortization Schedule'!E:E, 'Amortization Schedule'!A:A, ">="&((5-1)*12+1), 'Amortization Schedule'!A:A, "<="&(5*12)) -> 59142.41 | C9: =SUMIFS('Amortization Schedule'!G:G, 'Amortization Schedule'!A:A, ">="&((5-1)*12+1), 'Amortization Schedule'!A:A, "<="&(5*12)) -> 56432.27 | D9: =SUMIFS('Amortization Schedule'!F:F, 'Amortization Schedule'!A:A, ">="&((5-1)*12+1), 'Amortization Schedule'!A:A, "<="&(5*12)) -> 2710.29 | E9: =IFERROR(INDEX('Amortization Schedule'!H:H, MATCH(5*12, 'Amortization Schedule'!A:A, 0)), 0) -> 0
